docs/.gitignore
docs/Makefile
docs/conf.py
docs/conf.rst
docs/contents.rst
docs/ctl.rst
docs/hba.rst
docs/index.rst
docs/log.rst
docs/pgpass.rst
docs/service.rst
pgtoolkit/__init__.py
pgtoolkit/_helpers.py
pgtoolkit/conf.py
pgtoolkit/ctl.py
pgtoolkit/errors.py
pgtoolkit/hba.py
pgtoolkit/pgpass.py
pgtoolkit/py.typed
pgtoolkit/service.py
pgtoolkit/log/__init__.py
pgtoolkit/log/__main__.py
pgtoolkit/log/parser.py
pgtoolkit-0.33.0.dist-info/licenses/LICENSE
tests/datatests.sh
tests/test_conf.py
tests/test_ctl.py
tests/test_ctl_func.py
tests/test_hba.py
tests/test_helpers.py
tests/test_log.py
tests/test_pass.py
tests/test_service.py
tests/data/pg_hba.conf
tests/data/pg_hba_bad.conf
tests/data/pg_service.conf
tests/data/pg_service_bad.conf
tests/data/pgpass
tests/data/pgpass_bad
tests/data/postgres-my-my.conf
tests/data/postgres-my.conf
tests/data/postgres-mymymy.conf
tests/data/postgres.conf
tests/data/postgresql.log
tests/data/conf.d/.hidden.conf
tests/data/conf.d/.includeme
tests/data/conf.d/listen.conf
tests/data/conf.d/with-include.conf
pgtoolkit-0.33.0.dist-info/METADATA
pgtoolkit-0.33.0.dist-info/WHEEL
pgtoolkit-0.33.0.dist-info/top_level.txt
pgtoolkit-0.33.0.dist-info/RECORD
