Metadata-Version: 2.4
Name: pgtoolkit
Version: 0.33.0
Summary: PostgreSQL Support from Python
Author-email: Dalibo <contact@dalibo.com>
Maintainer-email: Denis Laxalde <denis.laxalde@dalibo.com>, Pierre Giraud <pierre.giraud@dalibo.com>, Julian Vanden Broeck <julian.vandenbroeck@dalibo.com>
License: PostgreSQL
Project-URL: Repository, https://github.com/dalibo/pgtoolkit
Project-URL: Documentation, https://pgtoolkit.readthedocs.io/
Keywords: postgresql,postgresql.conf,pg_hba,pgpass,pg_service.conf
Classifier: Development Status :: 3 - Alpha
Classifier: Intended Audience :: Developers
Classifier: License :: OSI Approved :: PostgreSQL License
Classifier: Programming Language :: Python :: 3
Classifier: Topic :: Database
Requires-Python: >=3.9
License-File: LICENSE
Provides-Extra: dev
Requires-Dist: pgtoolkit[doc,lint,test,typing]; extra == "dev"
Provides-Extra: lint
Requires-Dist: black; extra == "lint"
Requires-Dist: check-manifest; extra == "lint"
Requires-Dist: flake8; extra == "lint"
Requires-Dist: isort; extra == "lint"
Requires-Dist: pyupgrade; extra == "lint"
Provides-Extra: typing
Requires-Dist: mypy; extra == "typing"
Provides-Extra: test
Requires-Dist: pytest; extra == "test"
Requires-Dist: pytest-asyncio; extra == "test"
Requires-Dist: pytest-cov; extra == "test"
Requires-Dist: pytest-mock; extra == "test"
Requires-Dist: psycopg2-binary; extra == "test"
Provides-Extra: doc
Requires-Dist: sphinx; extra == "doc"
Requires-Dist: sphinx-autobuild; extra == "doc"
Requires-Dist: sphinx_rtd_theme; extra == "doc"
Dynamic: license-file
